geostates/__init__.py
geostates/plot.py
geostates/states.py
geostates/utils.py
geostates/shapefiles/__init__.py
geostates/shapefiles/cb_2018_us_county_500k/__init__.py
geostates/shapefiles/cb_2018_us_county_500k/cb_2018_us_county_500k.dbf
geostates/shapefiles/cb_2018_us_county_500k/cb_2018_us_county_500k.shp
geostates/shapefiles/cb_2018_us_county_500k/cb_2018_us_county_500k.shx
geostates/shapefiles/cb_2018_us_state_500k/__init__.py
geostates/shapefiles/cb_2018_us_state_500k/cb_2018_us_state_500k.dbf
geostates/shapefiles/cb_2018_us_state_500k/cb_2018_us_state_500k.shp
geostates/shapefiles/cb_2018_us_state_500k/cb_2018_us_state_500k.shx
geostates-0.1.2.dist-info/LICENSE.txt
geostates-0.1.2.dist-info/METADATA
geostates-0.1.2.dist-info/WHEEL
geostates-0.1.2.dist-info/top_level.txt
geostates-0.1.2.dist-info/RECORD
