Metadata-Version: 2.1
Name: geostates
Version: 0.1.2
Summary: A package for plotting choropleth maps
Home-page: https://github.com/eolesinski/geostates
Author: geostates
Author-email: eolesinski@nevada.unr.edu
Classifier: Programming Language :: Python :: 3
Classifier: License :: OSI Approved :: MIT License
Classifier: Operating System :: OS Independent
Requires-Python: >=3.6
License-File: LICENSE.txt
Requires-Dist: numpy
Requires-Dist: geopandas
Requires-Dist: matplotlib
